homieclient/__init__.py
homieclient/device.py
homieclient/node.py
homieclient-0.0.1.dist-info/LICENSE
homieclient-0.0.1.dist-info/METADATA
homieclient-0.0.1.dist-info/WHEEL
homieclient-0.0.1.dist-info/top_level.txt
homieclient-0.0.1.dist-info/RECORD
