Metadata-Version: 2.1
Name: homieclient
Version: 0.0.1
Summary: Client to interact with Homie IoT devices via MQTT
Home-page: https://github.com/michelwilson/homieclient
Author: Michel Wilson
Author-email: michel@crondor.net
License: MIT License
Platform: any
Classifier: License :: OSI Approved :: MIT License
Classifier: Programming Language :: Python :: 3
Classifier: Operating System :: OS Independent
Classifier: Topic :: Home Automation
Requires-Python: >=3.0
Requires-Dist: paho-mqtt (==1.5.1)
